MANIFEST.in
README.md
requirements.txt
setup.py
get_a_joke.egg-info/PKG-INFO
get_a_joke.egg-info/SOURCES.txt
get_a_joke.egg-info/dependency_links.txt
get_a_joke.egg-info/requires.txt
get_a_joke.egg-info/top_level.txt
joke_generator/__init__.py
joke_generator/jokes.py