Metadata-Version: 2.1
Name: get-a-joke
Version: 0.1.0
Summary: A Python package to generate jokes from external APIs.
Home-page: https://github.com/bipin-mishra1
Author: Bipin Mishra
Author-email: bipnm56567@gmail.com
License: UNKNOWN
Platform: UNKNOWN
